rank_eval/__init__.py
rank_eval/frozenset_dict.py
rank_eval/meta_functions.py
rank_eval/metrics.py
rank_eval/qrels.py
rank_eval/qrels_run_common.py
rank_eval/report.py
rank_eval/run.py
rank_eval/statistical_testing.py
rank_eval/utils.py
rank_eval-0.1.3.dist-info/LICENSE
rank_eval-0.1.3.dist-info/METADATA
rank_eval-0.1.3.dist-info/WHEEL
rank_eval-0.1.3.dist-info/top_level.txt
rank_eval-0.1.3.dist-info/RECORD
