Metadata-Version: 2.1
Name: rank-eval
Version: 0.1.3
Summary: rank_eval: A Blazing Fast Python Library for Ranking Evaluation and Comparison
Home-page: https://github.com/AmenRa/rank_eval
Author: Elias Bassani
Author-email: elias.bssn@gmail.com
License: UNKNOWN
Keywords: trec_eval,information retrieval,evaluation,ranking,numba
Platform: UNKNOWN
Classifier: Programming Language :: Python :: 3
Classifier: License :: OSI Approved :: MIT License
Classifier: Intended Audience :: Science/Research
Classifier: Operating System :: OS Independent
Classifier: Topic :: Text Processing :: General
Requires-Python: >=3.7
License-File: LICENSE
Requires-Dist: numpy
Requires-Dist: numba (>=0.54.1)
Requires-Dist: pandas
Requires-Dist: tabulate
Requires-Dist: tqdm
